hotfinger/__init__.py
hotfinger/__main__.py
hotfinger/data/hotfinger.json
hotfinger/data/hotfinger_v1.csv
hotfinger/data/hotfinger_v1.json
hotfinger/data/hotfinger_v2.json
hotfinger/data/hotfinger_v3.csv
hotfinger/data/hotfinger_v3.json
hotfinger/data/hotfinger_v4.json
hotfinger/data/hotfinger_v5.json
hotfinger/errfinger.json
hotfinger/finger_handle_tools/diffinger.json
hotfinger/finger_handle_tools/diffinger_tide.json
hotfinger/finger_handle_tools/errfinger.json
hotfinger/finger_handle_tools/finger_v4.json
hotfinger/finger_handle_tools/finger_v6.json
hotfinger/finger_handle_tools/handle_14.py
hotfinger/finger_handle_tools/handle_scj.py
hotfinger/finger_handle_tools/handle_tidefinger.py
hotfinger/finger_handle_tools/hotfinge2csv.py
hotfinger/finger_handle_tools/hotfinger_set.json
hotfinger/finger_handle_tools/remove_err_finger.py
hotfinger/finger_handle_tools/scj.json
hotfinger/finger_handle_tools/scj_v2.json
hotfinger/finger_handle_tools/scj_v3.json
hotfinger/finger_handle_tools/scj_v4.json
hotfinger/finger_handle_tools/tide.json
hotfinger/finger_handle_tools/tide2.json
hotfinger/finger_handle_tools/tide_set.json
hotfinger/finger_handle_tools/tmp.py
hotfinger/hotfinger.py
hotfinger-0.1.4.5.dist-info/WHEEL
hotfinger-0.1.4.5.dist-info/METADATA
hotfinger-0.1.4.5.dist-info/RECORD
