Metadata-Version: 2.1
Name: hotfinger
Version: 0.1.4.5
Summary: 
Author: zmf96
Author-email: zmf96@qq.com
Requires-Python: >=3.8,<4.0
Classifier: Programming Language :: Python :: 3
Classifier: Programming Language :: Python :: 3.10
Classifier: Programming Language :: Python :: 3.8
Classifier: Programming Language :: Python :: 3.9
Requires-Dist: bs4 (>=0.0.1,<0.0.2)
Requires-Dist: cp-common (>=0.1.8,<0.2.0)
Requires-Dist: loguru (>=0.6.0,<0.7.0)
Requires-Dist: lxml (>=4.8.0,<5.0.0)
Requires-Dist: python-Wappalyzer (>=0.3.1,<0.4.0)
